Metadata-Version: 2.1
Name: celery-custom-fix
Version: 4.2.0
Summary: Distributed Task Queue.
Home-page: http://celeryproject.org
Author: Ask Solem
Author-email: ask@celeryproject.org
License: BSD
Keywords: task job queue distributed messaging actor
Platform: any
Classifier: Development Status :: 5 - Production/Stable
Classifier: License :: OSI Approved :: BSD License
Classifier: Topic :: System :: Distributed Computing
Classifier: Topic :: Software Development :: Object Brokering
Classifier: Programming Language :: Python
Classifier: Programming Language :: Python :: 2
Classifier: Programming Language :: Python :: 2.7
Classifier: Programming Language :: Python :: 3
Classifier: Programming Language :: Python :: 3.4
Classifier: Programming Language :: Python :: 3.5
Classifier: Programming Language :: Python :: 3.6
Classifier: Programming Language :: Python :: 3.7
Classifier: Programming Language :: Python :: Implementation :: CPython
Classifier: Programming Language :: Python :: Implementation :: PyPy
Classifier: Operating System :: OS Independent
Requires-Python: >=2.7, !=3.0.*, !=3.1.*, !=3.2.*, !=3.3.*
Requires-Dist: pytz (>dev)
Requires-Dist: billiard (<3.6.0,>=3.5.0.2)
Requires-Dist: kombu (<5.0,>=4.2.0)
Provides-Extra: auth
Requires-Dist: cryptography ; extra == 'auth'
Provides-Extra: azureblockblob
Requires-Dist: azure-storage (==0.36.0) ; extra == 'azureblockblob'
Requires-Dist: azure-common (==1.1.5) ; extra == 'azureblockblob'
Requires-Dist: azure-storage-common (==1.1.0) ; extra == 'azureblockblob'
Provides-Extra: cassandra
Requires-Dist: cassandra-driver ; extra == 'cassandra'
Provides-Extra: consul
Requires-Dist: python-consul ; extra == 'consul'
Provides-Extra: cosmosdbsql
Requires-Dist: pydocumentdb (==2.3.2) ; extra == 'cosmosdbsql'
Provides-Extra: couchbase
Requires-Dist: couchbase ; extra == 'couchbase'
Requires-Dist: couchbase-cffi ; (platform_python_implementation == "PyPy") and extra == 'couchbase'
Provides-Extra: couchdb
Requires-Dist: pycouchdb ; extra == 'couchdb'
Provides-Extra: django
Requires-Dist: Django (>=1.8) ; extra == 'django'
Provides-Extra: dynamodb
Requires-Dist: boto3 (>=1.4.6) ; extra == 'dynamodb'
Provides-Extra: elasticsearch
Requires-Dist: elasticsearch ; extra == 'elasticsearch'
Provides-Extra: eventlet
Requires-Dist: eventlet ; extra == 'eventlet'
Provides-Extra: gevent
Requires-Dist: gevent ; extra == 'gevent'
Provides-Extra: librabbitmq
Requires-Dist: librabbitmq (>=1.5.0) ; extra == 'librabbitmq'
Provides-Extra: memcache
Requires-Dist: pylibmc ; extra == 'memcache'
Provides-Extra: mongodb
Requires-Dist: pymongo (>=3.3.0) ; extra == 'mongodb'
Provides-Extra: msgpack
Requires-Dist: msgpack-python (>=0.3.0) ; extra == 'msgpack'
Provides-Extra: pymemcache
Requires-Dist: python-memcached ; extra == 'pymemcache'
Provides-Extra: pyro
Requires-Dist: pyro4 ; extra == 'pyro'
Provides-Extra: redis
Requires-Dist: redis (>=2.10.5) ; extra == 'redis'
Provides-Extra: riak
Requires-Dist: riak (>=2.0) ; extra == 'riak'
Provides-Extra: s3
Requires-Dist: boto3 (>=1.4.6) ; extra == 's3'
Provides-Extra: slmq
Requires-Dist: softlayer-messaging (>=1.0.3) ; extra == 'slmq'
Provides-Extra: solar
Requires-Dist: ephem ; extra == 'solar'
Provides-Extra: sqlalchemy
Requires-Dist: sqlalchemy ; extra == 'sqlalchemy'
Provides-Extra: sqs
Requires-Dist: boto3 (>=1.4.6) ; extra == 'sqs'
Requires-Dist: pycurl ; extra == 'sqs'
Provides-Extra: tblib
Requires-Dist: tblib (>=1.3.0) ; extra == 'tblib'
Provides-Extra: yaml
Requires-Dist: PyYAML (>=3.10) ; extra == 'yaml'
Provides-Extra: zookeeper
Requires-Dist: kazoo (>=1.3.1) ; extra == 'zookeeper'
